{
    "c": [
        {
            "v": "צֹחַר",
            "f": null
        },
        {
            "v": "1. אחד מבני שמעון\n2. אבי עפרון החתי בימי אברהם\n3. בן אשחור לשבט יהודה מאשתו חלאה",
            "f": null
        },
        {
            "v": "1. בראשית מו י\n2. בראשית כג ח\n3. דה\"י א ד ז",
            "f": null
        },
        {
            "v": "3. בדה\"י (א ד כג), הוא מכונה זֶרַח, וכנראה מדובר באותו אדם\n\n2. לא מזרע ישראל",
            "f": null
        },
        {
            "v": "צחור = לבן",
            "f": null
        },
        {
            "v": null,
            "f": null
        }
    ]
}
