{
    "c": [
        {
            "v": "אַבְרָהָם, אַבְרָם",
            "f": null
        },
        {
            "v": "אבינו",
            "f": null
        },
        {
            "v": "בראשית יח יט",
            "f": null
        },
        {
            "v": "אַבְרָם - שמו הקודם של אברהם אבינו (בראשית יא כו)",
            "f": null
        },
        {
            "v": "בתחילה אברם - אב לארם, ואח\"כ אברהם - כִּי אַב הֲמוֹן גּוֹיִם נְתַתִּיךָ",
            "f": null
        },
        {
            "v": null,
            "f": null
        }
    ]
}
