{
    "c": [
        {
            "v": "אֲחִיָּה, אֲחִיָּהוּ",
            "f": null
        },
        {
            "v": "1. בן אחיטוב, כוהן בשילה\n2. השילוני, נביא בימי שלמה\n3. אביו של המלך בעשא לשבט יששכר\n4. אחד מבני ירחמאל לשבט יהודה\n5. אחד מבני אחוד, מראשי אבות בנימין\n6. אחד הלוויים בימי דויד המלך\n7. הפלוני, אחד מגיבורי דוד\n8. אחד מסופרי המלך שלמה\n9. אחד מראשי העם שחתמו על האמנה בימי נחמיה",
            "f": null
        },
        {
            "v": "1. שמואל א יד ג\n2. מלכים א יא כט\n3. מלכים א טו כז\n4. דה\"י א ב כה\n5. דה\"י א ח ז\n6. דה\"י א כו כ\n7. דה\"י א יא לו\n8. מלכים א ד ג\n9. נחמיה י כז",
            "f": null
        },
        {
            "v": "2. מופיע גם אֲחִיָּהוּ (מלכים א יד ד)",
            "f": null
        },
        {
            "v": "ה' הוא אחי=ידידי",
            "f": null
        }
    ]
}
