{
    "c": [
        {
            "v": "אֶלְיָשִׁיב",
            "f": null
        },
        {
            "v": "1. מהכוהנים בימי דוד\n2. מצאצאיו של זרובבל\n3. השֵם של שלושה אנשים בימי עזרא, שנשאו נשים נוכריות ונבדלו מהן\n4. הכוהן הגדול בימי נחמיה",
            "f": null
        },
        {
            "v": "1. דה\"י א כד יב\n2. דה\"י א ג כד\n3. עזרא י פסוקים כד, כו, לו\n4. נחמיה ג א",
            "f": null
        },
        null,
        {
            "v": "האל ישיב שבות עמו לארצו",
            "f": null
        },
        {
            "v": null,
            "f": null
        }
    ]
}
