{
    "c": [
        {
            "v": "שֶׁנְאַצַּר",
            "f": null
        },
        {
            "v": "בנו (או צאצאו) של יכניה (יהויכין) מלך יהודה",
            "f": null
        },
        {
            "v": "דה\"י א ג יח",
            "f": null
        },
        {
            "v": "יש המשערים שאולי הוא שֵׁשְׁבַּצַּר (עזרא א ח)",
            "f": null
        },
        {
            "v": "שם בבלי: אפשר שהוא מקוצר משין (=האל סין) שר-אצר (נצור את המלך)",
            "f": null
        },
        {
            "v": null,
            "f": null
        }
    ]
}
