{
    "c": [
        {
            "v": "מְשִׁלֵּמוֹת, מְשִׁלֵּמִית",
            "f": null
        },
        {
            "v": "מראשי המדינה שישבו בירושלים בימי נחמיה\n\nאבי ברכיהו מבני אפרים בימי אחז מלך יהודה",
            "f": null
        },
        {
            "v": "נחמיה יא יג\n\nדה\"י ב כח יב",
            "f": null
        },
        {
            "v": "לפי האנציקלופדיה לאישים בתנ\"ך, יש רק משילמות",
            "f": null
        },
        {
            "v": "ה' יעניק שלום ושלמות",
            "f": null
        },
        {
            "v": null,
            "f": null
        }
    ]
}
