{
    "c": [
        {
            "v": "יְרַחְמְאֵל",
            "f": null
        },
        {
            "v": "בן קיש לבני מררי\n\nבן המלך שנשלח על ידי יהויקים מלך יהודה עם עוד שני אנשים לאסור את ירמיה הנביא\n\nבנו בכורו של חצרון בן פרץ בן יהודה",
            "f": null
        },
        {
            "v": "דה\"י א כד כט\n\nירמיה לו כו\n\nדה\"י א ב ט",
            "f": null
        },
        null,
        {
            "v": "ה' ירחם=יאהב",
            "f": null
        },
        {
            "v": null,
            "f": null
        }
    ]
}
